{
  "openapi": "3.0.3",
  "info": {
    "title": "User API - Register User",
    "version": "1.0.0",
    "description": "Registers a new user."
  },
  "servers": [
    {
      "url": "/api/v1",
      "description": "Base URL for the API"
    }
  ],
  "components": {
    "$ref": "./components.json"
  },
  "paths": {
    "/auth/register": {
      "post": {
        "tags": ["Authentication"],
        "summary": "Register a new user",
        "operationId": "registerUser",
        "requestBody": {
          "content": {
            "application/json": {
              "schema": {
                "$ref": "#/components/schemas/RegisterRequest"
              }
            }
          }
        },
        "responses": {
          "201": {
            "description": "User successfully registered",
            "content": {
              "application/json": {
                "schema": {
                  "$ref": "#/components/schemas/AuthResponse"
                }
              }
            }
          },
          "400": {
            "description": "Bad Request - Invalid input data",
            "content": {
              "application/json": {
                "schema": {
                  "$ref": "#/components/schemas/Error"
                }
              }
            }
          },
          "409": {
            "description": "Conflict - Email already exists",
            "content": {
              "application/json": {
                "schema": {
                  "$ref": "#/components/schemas/Error"
                }
              }
            }
          }
        }
      }
    }
  }
}
